trytond/modules/investment/README.rst
trytond/modules/investment/__init__.py
trytond/modules/investment/asset.py
trytond/modules/investment/asset.xml
trytond/modules/investment/const.py
trytond/modules/investment/cron.py
trytond/modules/investment/cron.xml
trytond/modules/investment/diagram.py
trytond/modules/investment/diagram.xml
trytond/modules/investment/group.xml
trytond/modules/investment/icon.xml
trytond/modules/investment/identifier.py
trytond/modules/investment/import_wiz.py
trytond/modules/investment/import_wiz.xml
trytond/modules/investment/menu.xml
trytond/modules/investment/message.xml
trytond/modules/investment/onlinesource.py
trytond/modules/investment/onlinesource.xml
trytond/modules/investment/rate.py
trytond/modules/investment/rate.xml
trytond/modules/investment/sources_def.xml
trytond/modules/investment/tryton.cfg
trytond/modules/investment/update_wiz.py
trytond/modules/investment/update_wiz.xml
trytond/modules/investment/versiondep.txt
trytond/modules/investment/icon/asset.svg
trytond/modules/investment/icon/gain_invest.svg
trytond/modules/investment/icon/stockonline.svg
trytond/modules/investment/locale/de.po
trytond/modules/investment/locale/en.po
trytond/modules/investment/scripts/__init__.py
trytond/modules/investment/scripts/import_investment_historicalrates.py
trytond/modules/investment/tests/__init__.py
trytond/modules/investment/tests/asset.py
trytond/modules/investment/tests/rate.py
trytond/modules/investment/tests/source.py
trytond/modules/investment/tests/test_module.py
trytond/modules/investment/tests/wizard.py
trytond/modules/investment/view/asset_form.xml
trytond/modules/investment/view/asset_list.xml
trytond/modules/investment/view/import_start_form.xml
trytond/modules/investment/view/rate_form.xml
trytond/modules/investment/view/rate_graph.xml
trytond/modules/investment/view/rate_list.xml
trytond/modules/investment/view/source_form.xml
trytond/modules/investment/view/source_list.xml
mds_investment-7.0.26.dist-info/METADATA
mds_investment-7.0.26.dist-info/WHEEL
mds_investment-7.0.26.dist-info/entry_points.txt
mds_investment-7.0.26.dist-info/top_level.txt
mds_investment-7.0.26.dist-info/RECORD
