Metadata-Version: 2.1
Name: mds-investment
Version: 7.0.26
Summary: Tryton module to add investment items.
Home-page: https://www.m-ds.de/
Author: martin-data services
Author-email: service@m-ds.de
License: GPL-3
Download-URL: https://scmdev.m-ds.de/Tryton/Extra/investment
Keywords: tryton investment shares commodities
Platform: UNKNOWN
Classifier: Development Status :: 5 - Production/Stable
Classifier: Environment :: Plugins
Classifier: Framework :: Tryton
Classifier: Intended Audience :: Developers
Classifier: Intended Audience :: Customer Service
Classifier: Intended Audience :: Information Technology
Classifier: Intended Audience :: Financial and Insurance Industry
Classifier: Topic :: Office/Business
Classifier: Topic :: Office/Business :: Financial :: Accounting
Classifier: Natural Language :: German
Classifier: Natural Language :: English
Classifier: Operating System :: OS Independent
Classifier: License :: OSI Approved :: GNU General Public License (GPL)
Classifier: Programming Language :: Python :: 3.7
Classifier: Programming Language :: Python :: 3.8
Classifier: Programming Language :: Python :: 3.9
Requires-Dist: html2text
Requires-Dist: requests (>=2.26)
Requires-Dist: trytond (<7.1,>=7.0)
Requires-Dist: trytond-company (<7.1,>=7.0)
Requires-Dist: trytond-currency (<7.1,>=7.0)
Requires-Dist: trytond-product (<7.1,>=7.0)
